types_acgi/__init__.py
types_acgi/py.typed
types_acgi-0.8.0.dist-info/WHEEL
types_acgi-0.8.0.dist-info/METADATA
types_acgi-0.8.0.dist-info/RECORD
