Metadata-Version: 2.3
Name: types-acgi
Version: 0.8.0
Summary: Add your description here
Author: jack.burridge
Author-email: jack.burridge <jack.burridge@mail.com>
Classifier: Development Status :: 2 - Pre-Alpha
Classifier: Framework :: AsyncIO
Classifier: Programming Language :: Python :: 3 :: Only
Classifier: Programming Language :: Python :: 3.11
Classifier: Programming Language :: Python :: 3.12
Classifier: Programming Language :: Python :: 3.13
Requires-Python: >=3.11
Project-URL: Changelog, https://github.com/asyncfast/acgi/blob/main/CHANGELOG.md
Project-URL: Homepage, https://github.com/asyncfast/acgi/tree/main/packages/types-acgi
Project-URL: Issues, https://github.com/asyncfast/acgi/issues
Project-URL: Repository, https://github.com/asyncfast/acgi/tree
